{
  "publicPath": "/static/",
  "all": [
    "polyfills.0145c7cdf3365e3c843f.bundle.js",
    "main.3d969dcb85d5bc38ccd0.bundle.js",
    "vendor.cb78913f0e4ea3314a80.bundle.js",
    "manifest.a4b80466234114bfb35d.bundle.js"
  ],
  "initial": [
    "manifest.a4b80466234114bfb35d.bundle.js",
    "polyfills.0145c7cdf3365e3c843f.bundle.js",
    "vendor.cb78913f0e4ea3314a80.bundle.js",
    "main.3d969dcb85d5bc38ccd0.bundle.js"
  ],
  "async": [],
  "modules": {
    "38727914": [
      0
    ],
    "53095314": [
      2
    ],
    "3b230b78": [
      0
    ],
    "82bb91b0": [
      0
    ],
    "22e86084": [
      0
    ],
    "da532d3a": [
      2
    ],
    "4dbe6229": [
      0
    ],
    "3658a83d": [
      0
    ],
    "48ed0941": [
      0
    ],
    "12aded5f": [
      0
    ],
    "6f6e442e": [
      0
    ],
    "504196ac": [
      0
    ],
    "749f6444": [
      0
    ],
    "7efff9ee": [
      0
    ],
    "181709a9": [
      0
    ],
    "7e62b188": [
      0
    ],
    "664a6d67": [
      0
    ],
    "3fb4a4f7": [
      2
    ],
    "423c6f1a": [
      0
    ],
    "1b983264": [
      0
    ],
    "43f5283f": [
      0
    ],
    "0c2e621a": [
      0
    ],
    "e142bf56": [
      0
    ],
    "96c26958": [
      0
    ],
    "52c0a75e": [
      0
    ],
    "4a8a5893": [
      2
    ],
    "7b3d7e16": [
      2
    ],
    "9f4d1c2c": [
      2
    ],
    "493dbf26": [
      0
    ],
    "07b9eae4": [
      0
    ],
    "b65930cc": [
      0
    ],
    "bf03ea9a": [
      0
    ],
    "26b0c628": [
      0
    ],
    "7ea03d12": [
      0
    ],
    "5bb4d07e": [
      0
    ],
    "c681676a": [
      0
    ],
    "08c4982a": [
      0
    ],
    "6105b320": [
      0
    ],
    "888f01f4": [
      0
    ],
    "62fc4818": [
      0
    ],
    "06296b6c": [
      1
    ],
    "5ab93018": [
      1
    ],
    "91d5e5ba": [
      2
    ],
    "3f6fba9b": [
      1
    ],
    "10c98846": [
      1
    ],
    "7c0bdf70": [
      1
    ],
    "25abebb6": [
      1
    ],
    "78acbbd8": [
      1
    ],
    "0478027a": [
      1
    ],
    "36a0391e": [
      1
    ],
    "c7d65c70": [
      2
    ],
    "4765111a": [
      1
    ],
    "bef8790e": [
      2
    ],
    "64b23539": [
      1
    ],
    "749f760e": [
      1
    ],
    "55d9c00c": [
      1
    ],
    "22b1cbd7": [
      2
    ],
    "080cf97c": [
      2
    ],
    "2b160f09": [
      2
    ],
    "6185635d": [
      2
    ],
    "3807b7de": [
      1
    ],
    "779ce6df": [
      0
    ],
    "f385a564": [
      0
    ],
    "619705ca": [
      0
    ],
    "aa57cc58": [
      0
    ],
    "b4e4d314": [
      0
    ],
    "10c90385": [
      0
    ],
    "6922ebf4": [
      0
    ],
    "10706fd2": [
      0
    ],
    "468dd039": [
      0
    ],
    "2a2eb19c": [
      0
    ],
    "5d2a3543": [
      0
    ],
    "223aeedb": [
      0
    ],
    "7216db8c": [
      0
    ],
    "3ff99875": [
      0
    ],
    "1ff540da": [
      0
    ],
    "49fc5952": [
      0
    ],
    "9ba7e1a8": [
      0
    ],
    "69970c7b": [
      0
    ],
    "9360533c": [
      0
    ],
    "7edca1c2": [
      0
    ],
    "22049b15": [
      0
    ],
    "4841e724": [
      0
    ],
    "b1f49320": [
      0
    ],
    "106dacf0": [
      0
    ],
    "02c1c6d4": [
      0
    ],
    "5a6d450a": [
      0
    ],
    "0f84513a": [
      0
    ],
    "3ff1ca33": [
      0
    ],
    "2c8762da": [
      0
    ],
    "7c298c7c": [
      0
    ],
    "4e6ef16e": [
      0
    ],
    "48ad9669": [
      0
    ],
    "2943f35c": [
      0
    ],
    "7dadb4cb": [
      0
    ]
  }
}